inwords
