Metadata-Version: 2.1
Name: inwords
Version: 1.0.3
Summary: A Python package to spell out a number
Home-page: https://github.com/s18k/inwords
Author: Shreyas Kamath
Author-email: shreyaskamath18@gmail.com
License: GNU General Public License v3.0
Download-URL: https://github.com/s18k/inwords//archive/inwords-1.0.3
Platform: UNKNOWN
Classifier: Programming Language :: Python :: 3
Classifier: License :: OSI Approved :: GNU General Public License v3 (GPLv3)
Classifier: Operating System :: OS Independent
